intellect_utils/__init__.py
intellect_utils/blas_utils.py
intellect_utils/dask_utils.py
intellect_utils/jit_utils.py
intellect_utils/mkl_utils.py
intellect_utils/onnx_utils.py
intellect_utils/parallel_utils.py
intellect_utils/ray_utils.py
intellect_utils/torch_tf_utils.py
intellectutils-0.1.0b0.dist-info/licenses/LICENSE
intellectutils-0.1.0b0.dist-info/METADATA
intellectutils-0.1.0b0.dist-info/WHEEL
intellectutils-0.1.0b0.dist-info/top_level.txt
intellectutils-0.1.0b0.dist-info/RECORD
