Metadata-Version: 2.4
Name: IntellectUtils
Version: 0.1.0b0
Summary: High-performance CPU utilities for AI training and parallel computation
Home-page: https://github.com/LaserRay1234/IntellectUtils
Author: Your Name
Author-email: your.email@example.com
Classifier: Development Status :: 4 - Beta
Classifier: Programming Language :: Python :: 3
Classifier: Intended Audience :: Developers
Classifier: Topic :: Scientific/Engineering :: Artificial Intelligence
Classifier: License :: OSI Approved :: MIT License
Requires-Python: >=3.7
License-File: LICENSE
Requires-Dist: numba
Requires-Dist: joblib
Requires-Dist: dask
Requires-Dist: ray
Requires-Dist: onnxruntime
Requires-Dist: torch
Requires-Dist: tensorflow
Requires-Dist: threadpoolctl
Provides-Extra: dev
Requires-Dist: pytest; extra == "dev"
Requires-Dist: black; extra == "dev"
Requires-Dist: flake8; extra == "dev"
Dynamic: author
Dynamic: author-email
Dynamic: classifier
Dynamic: description
Dynamic: description-content-type
Dynamic: home-page
Dynamic: license-file
Dynamic: provides-extra
Dynamic: requires-dist
Dynamic: requires-python
Dynamic: summary
